synth_spectra/__init__.py
synth_spectra/config.py
synth_spectra/plotting.py
synth_spectra/spectrum_utils.py
synth_spectra-1.0.0.dist-info/licenses/LICENSE
synth_spectra-1.0.0.dist-info/METADATA
synth_spectra-1.0.0.dist-info/WHEEL
synth_spectra-1.0.0.dist-info/top_level.txt
synth_spectra-1.0.0.dist-info/RECORD
