Metadata-Version: 2.4
Name: synth_spectra
Version: 1.0.0
Summary: A package to generate synthetic spectra for testing purposes.
Author-email: Ashley Bemis <arbemis@gmail.com>, Annabella Meech <annabella.meech@cfa.harvard.edu>
Project-URL: Homepage, https://github.com/ashleyrbemis/synth_spectra
Project-URL: Issues, https://github.com/ashleyrbemis/synth_spectra/issues
Classifier: Programming Language :: Python :: 3
Classifier: License :: OSI Approved :: MIT License
Classifier: Operating System :: OS Independent
Requires-Python: >=3.8
License-File: LICENSE
Requires-Dist: numpy
Requires-Dist: matplotlib
Requires-Dist: scipy
Dynamic: license-file
